{"version":1,"resource":"file:///home/farabi-dev/Codes/Projects/work/moonly/apps/backend/src/resolvers/account-linking.ts","entries":[{"id":"x133.ts","timestamp":1683606306238},{"id":"omcM.ts","timestamp":1683609818566},{"id":"PurO.ts","timestamp":1683613307138},{"id":"3V7P.ts","timestamp":1683613440845},{"id":"USZz.ts","timestamp":1683613483900},{"id":"K7a3.ts","timestamp":1683615601486},{"id":"ImON.ts","timestamp":1683615700424},{"id":"Bujj.ts","timestamp":1683615730968},{"id":"cjVn.ts","timestamp":1683640952762},{"id":"pnae.ts","timestamp":1683641462545},{"id":"L0xI.ts","timestamp":1683642648798},{"id":"iImt.ts","timestamp":1683642927458},{"id":"6pKn.ts","timestamp":1683643061776},{"id":"AFHO.ts","timestamp":1683643164138},{"id":"vrRw.ts","timestamp":1683643329644},{"id":"NPDn.ts","timestamp":1683643413843},{"id":"nGQz.ts","timestamp":1683643519825},{"id":"bECU.ts","timestamp":1683662992471},{"id":"uXVu.ts","timestamp":1683663649413},{"id":"K9yf.ts","timestamp":1683671198800},{"id":"Y2A0.ts","timestamp":1683671228940},{"id":"2ZAp.ts","timestamp":1683693550330},{"id":"gyQO.ts","timestamp":1683694088363},{"id":"Usvb.ts","timestamp":1684232058114},{"id":"Fnzi.ts","timestamp":1684293878407},{"id":"VORg.ts","timestamp":1684294438015},{"id":"wrvC.ts","timestamp":1684294691571},{"id":"qjti.ts","timestamp":1684294858384},{"id":"o2Rn.ts","timestamp":1684295083917},{"id":"P72t.ts","source":"Workspace Edit","timestamp":1684303636736},{"id":"kP54.ts","timestamp":1684314666863},{"id":"Hjef.ts","timestamp":1684314834729},{"id":"psHn.ts","timestamp":1684314848177},{"id":"nvgm.ts","timestamp":1684315224667},{"id":"UKr1.ts","timestamp":1684315257923},{"id":"ndJW.ts","timestamp":1684315822425}]}