{"version":1,"resource":"file:///home/farabi-dev/Codes/Projects/Md-Abu-Taher-Projects/Quote-API/src/handlers/messageCreateHandler.ts","entries":[{"id":"0g0x.ts","source":"Add import from \"../interfaces/QuoteAPIResponse\"","timestamp":1680143293322},{"id":"YXfp.ts","timestamp":1680143357497},{"id":"5qlr.ts","timestamp":1680143489586},{"id":"ZtX2.ts","timestamp":1680144599078},{"id":"2pDc.ts","timestamp":1680144763178},{"id":"wRCE.ts","timestamp":1680146584381},{"id":"nAjQ.ts","source":"undoRedo.source","timestamp":1680164293934},{"id":"387J.ts","timestamp":1680166058058},{"id":"oZhQ.ts","timestamp":1680170691565},{"id":"OXVD.ts","timestamp":1680170723043},{"id":"xcDV.ts","timestamp":1680171641830},{"id":"HbKi.ts","timestamp":1680172033125},{"id":"N3Hd.ts","timestamp":1680172134434},{"id":"JEUL.ts","timestamp":1680172147006},{"id":"2d2o.ts","timestamp":1680172210816},{"id":"e40s.ts","timestamp":1680172368485},{"id":"SDKh.ts","timestamp":1680172411372},{"id":"VrkK.ts","timestamp":1680172491310},{"id":"iWiu.ts","timestamp":1680212906298},{"id":"Ivji.ts","timestamp":1680213069371},{"id":"5AfM.ts","timestamp":1680215301128},{"id":"HN7O.ts","timestamp":1680216356178},{"id":"I6Fy.ts","timestamp":1680217221781},{"id":"Jpx6.ts","timestamp":1680217735351},{"id":"hGvF.ts","source":"Workspace Edit","timestamp":1680218007155},{"id":"CBgB.ts","timestamp":1680218383507},{"id":"C7ZD.ts","source":"Workspace Edit","timestamp":1680218508037}]}